Workbook

Sheet Process Flow
A1: Eb-ODM — Master Process Flow
A2: 227 steps across 8 categories. Sequential for the first 30 steps, then three parallel design tracks (Hardware · Firmware · Enclosure) run concurrently and re-merge at the Prototype Checklist. Source: Eb_ODM_Process_Steps_FULL — Sheet1, rows 20–183. Sales steps (source rows 5–19) excluded.
A3: Owner is the Project Manager throughout: the PM is accountable for the gate. Responsibility names the function that performs the work. Template Link holds the target filename under the Elecbits naming convention — these are targets to create, not live URLs. Replace [ProjectID] per project.
C4: Steps | D4: Action which need to be done in terms of written context | H4: Template / Sheet which need to be worked upon | I4: Which template to open, and what to do inside it | N4: Stakeholder | P4: Guidelines which need to follow
A5: S. No. | B5: Category | C5: Steps | D5: Entry Trigger | E5: Exit Trigger | F5: Entry Question | G5: Exit Question | H5: Template Link | I5: Template ID | J5: Template to work on | K5: Open | L5: Action | M5: What to do in the template | N5: Owner | O5: Responsibility | P5: Guidelines
A6: 1 | B6: 1 · Pre-design Feasibility | C6: Product strategy fit & sanction by Management | D6: PO received and project handed to PM | E6: Management sanction recorded and project moved out of Data Gather stage | F6: Is this product aligned with what we intend to build, and do we have the capability and capacity now? | G6: Has management sanctioned scope, budget envelope and team, in writing? | H6: [ProjectID]_Product-strategy-fit-and-sanction-by-Management_v1.0 | I6: EB-T-133 | J6: Internal MoM | K6: Open | L6: Create from template | M6: Open a new Internal MoM and record the sanction: scope, budget ceiling, timeline and the named person who approved each. A sanction that lives only in a conversation cannot be pointed at later. | N6: Project Manager | O6: Management / Project Manager | P6: Test the project against three things before committing resource: strategic fit, technical capability, and current capacity against the other live projects. A project that is technically deliverable but arrives when the hardware team is already fully committed will damage two projects rather than one. Record the sanction with its conditions — sanction with an unstated caveat is not sanction. This is the gate that moves the project out of Data Gather.
A7: 2 | B7: 1 · Pre-design Feasibility | C7: Product Vision & Objective | D7: Project sanctioned | E7: Vision and objective statement written and agreed with client | F7: Do we know who the end user is and what success looks like for them? | G7: Can every downstream design decision be traced back to a stated objective? | H7: [ProjectID]_Product-Vision-and-Objective_v1.0 | I7: EB-T-141 | J7: Product Features & Risk Management | K7: Open | L7: Create from template | M7: Create the file and fill the vision block: who the end user is, what problem the product solves, and the three features that decide whether it succeeds. Leave the risk table empty for now. | N7: Project Manager | O7: Project Manager / Product | P7: Write down what the product is for, who uses it, and what measurable outcome defines success — in a page, not a deck. This is the reference the team returns to when a design trade-off has no obvious answer. Vague objectives ('a good IoT gateway') resolve nothing; specific ones ('runs 18 months on two AA cells in an unheated outdoor cabinet') resolve most things. Agree it with the client so it is a shared reference, not our interpretation.
A8: 3 | B8: 1 · Pre-design Feasibility | C8: Budget allocation | D8: Vision and scope agreed | E8: Budget approved and loaded against the Project ID | F8: Have vendor quotes been collected for the major cost drivers before timelines are committed? | G8: Is there a costed line for BOM, PCB, assembly, logistics and enclosures, with contingency stated? | H8: [ProjectID]_Budget-allocation_v1.0 | I8: EB-T-148 | J8: Project Budget | K8: Open | L8: Create from template | M8: Create the budget and enter a costed line for BOM, PCB, assembly, enclosure, tooling, test and certification. Each line carries the vendor quote it came from. | N8: Project Manager | O8: Project Manager / Costing | P8: Build the budget from vendor quotes, not from memory of the last project. Collect quotes for the major cost drivers first — cells, main IC, enclosure tooling, certification — because these dominate and they move. Load the five expense categories (BoM, PCB, Assembly, Logistics, Enclosures) against the Project ID with an approval line, so actual expense can be tracked against plan per category. State contingency explicitly rather than padding line items.
A9: 4 | B9: 1 · Pre-design Feasibility | C9: Team finalisation & allocation | D9: Budget approved | E9: Team allocated and recorded in CPTS with availability confirmed | F9: Is one accountable owner named per domain, and is that person actually available? | G9: Does any allocated person have a conflicting commitment on another live project in the same window? | H9: [ProjectID]_Team-finalisation-and-allocation_v1.0 | I9: EB-T-147 | J9: Project Plan | K9: Open | L9: Add details | M9: Add the resource table: one accountable owner per domain, their allocation percentage, and their other live commitments. Flag anyone allocated above 100%. | N9: Project Manager | O9: Project Manager / Department Leads | P9: Name one accountable owner per domain — hardware, firmware, enclosure, testing. Shared ownership is prohibited; two names against one deliverable reliably produces neither. Check availability against the other live projects before confirming, not after: allocation conflicts discovered at execution are the most common cause of silent schedule slip. Record the allocation in CPTS so capacity is visible across the portfolio.
A10: 5 | B10: 1 · Pre-design Feasibility | C10: Milestone setting & project checkpoints | D10: Team allocated | E10: Milestone plan baselined and shared with client | F10: Are milestones tied to demonstrable artefacts rather than to elapsed time? | G10: Does each milestone have a defined deliverable, an owner and an acceptance test? | H10: [ProjectID]_Milestone-setting-and-project-checkpoints_v1.0 | I10: EB-T-151 | J10: Milestone Tracking Sheet | K10: Open | L10: Create from template | M10: Create the tracker and enter each milestone against a demonstrable artefact, not a date alone. Every milestone needs a deliverable that can be shown. | N10: Project Manager | O10: Project Manager | P10: Set milestones against artefacts that can be shown — schematic release, first article, DVT report — not against calendar quarters. Each milestone needs a deliverable, an owner and a test that decides whether it is met. Align payment milestones with these so commercial and technical progress cannot diverge. Baseline the plan; subsequent movement is tracked as variance against the baseline rather than by quietly editing dates.
A11: 6 | B11: 1 · Pre-design Feasibility | C11: LLD for developer | D11: Milestones set and engineering team allocated | E11: Designer LLD issued to hardware, firmware and enclosure leads | F11: Is the customer LLD locked, and is the requirement set complete enough to specify to a designer? | G11: Can a designer start work from this document without asking clarifying questions? | H11: [ProjectID]_LLD-for-developer_v1.0 | I11: EB-T-144 | J11: LLD | K11: Open | L11: Create from template | M11: Create the developer LLD from the customer LLD. Add the internal detail a designer needs: rails, interfaces, peripheral map, mechanical envelope, and the assumptions behind each. | N11: Project Manager | O11: Solution Architect / Project Manager | P11: This is the internal engineering specification, distinct from the customer LLD. Work through the 21-step structure: I/O count with 20–30% margin, MCU selection criteria, module-versus-discrete decisions, multi-source alternates, and the hardware-to-firmware interface definition. No execution task proceeds without both the Customer LLD and the Designer LLD locked — this gate is non-negotiable and holds under schedule pressure. Test the document by asking whether a designer could start from it cold.
A12: 7 | B12: 1 · Pre-design Feasibility | C12: PCB ID assignment (Eb-PCB) | D12: Designer LLD issued and board count known | E12: Eb-PCB IDs issued for every board and recorded in the ID registry | F12: How many distinct boards does this product need, and is each one identified? | G12: Does every board in the architecture have its own ID and revision field? | H12: [ProjectID]_PCB-ID-assignment-Eb-PCB_v1.0 | I12: EB-T-147 | J12: Project Plan | K12: Open | L12: Add details | M12: Record the allocated PCB ID(s) against the project. One ID per board, issued once, never reused. | N12: Project Manager | O12: Project Manager | P12: Assign Eb-PCB-[ProjectID]-[Rev] for each distinct board. Products with a main board plus a daughter or display board need separate IDs from the outset — retrofitting a second ID after layout has started leaves two months of files under the wrong name. Record every ID in the ID registry alongside the Client, Project and Product IDs so there is one place to resolve any identifier.
A13: 8 | B13: 1 · Pre-design Feasibility | C13: FW ID assignment (Eb-FW) | D13: Designer LLD issued and firmware images scoped | E13: Eb-FW IDs issued and linked to the corresponding PCB IDs | F13: How many distinct firmware images does this product need (application, bootloader, production test)? | G13: Is each firmware ID linked to the board revision it targets? | H13: [ProjectID]_FW-ID-assignment-Eb-FW_v1.0 | I13: EB-T-147 | J13: Project Plan | K13: Open | L13: Add details | M13: Record the allocated firmware ID(s) and which board each one runs on. | N13: Project Manager | O13: Project Manager / Firmware Lead | P13: Assign a firmware ID per distinct image and link each to the PCB ID and revision it targets. The firmware-to-board-revision link is what allows a returned unit to be diagnosed two years later; without it, 'which build is on this board' becomes unanswerable. Include production-test firmware in the scope — it is a real deliverable with its own lifecycle, not a script someone keeps locally.
A14: 9 | B14: 1 · Pre-design Feasibility | C14: Sales → PM handover | D14: Project ID issued and PM assigned | E14: Handover meeting held and PM confirms ownership | F14: Has Sales attached the client MoM, questionnaire responses, LLD and PO to the handover? | G14: Does the PM have every commitment Sales made, including verbal ones? | H14: [ProjectID]_Sales-PM-handover_v1.0 | I14: EB-T-133 | J14: Internal MoM | K14: Open | L14: Add details | M14: Add the handover MoM: what Sales committed to, what is documented, and every commitment that exists only verbally. The verbal ones are the risk. | N14: Project Manager | O14: Sales / Project Manager | P14: Hold this as a meeting, not a file transfer. The critical content is the commitments Sales made that are not in the documents — timeline hints, feature reassurances, pricing signals. Surface them now, because they will surface later as client expectations regardless. After handover Sales steps back and the PM owns the engagement end to end, with one named communication route to the client.
A15: 10 | B15: 1 · Pre-design Feasibility | C15: Engineering Kickoff | D15: Handover complete and Designer LLD issued | E15: Kickoff held, MoM circulated, first tasks assigned | F15: Have the engineering leads read the LLD before the meeting? | G15: Does every lead know their first deliverable and its date? | H15: [ProjectID]_Engineering-Kickoff_v1.0 | I15: EB-T-133 | J15: Internal MoM | K15: Open | L15: Add details | M15: Add the kickoff MoM: attendees, the scope as engineering understands it, and every open question with a named owner and a date. | N15: Project Manager | O15: Project Manager / Engineering Leads | P15: Write the plan into the MoM before the meeting starts — the MoM pre-exists the meeting rather than being captured during it, which converts the session from a briefing into a review. Walk the LLD, the architecture and the risk plan. Close with each lead's first deliverable and date recorded. Leads who have not read the LLD beforehand should say so and the kickoff should be moved rather than run hollow.
A16: 11 | B16: 1 · Pre-design Feasibility | C16: Access provisioning to team | D16: Team allocated and kickoff held | E16: All access granted and confirmed by each team member | F16: Does every allocated person have the tools, repositories and folders they need? | G16: Has each person confirmed they can actually open what they were granted? | H16: [ProjectID]_Access-provisioning-to-team_v1.0 | I16: EB-T-147 | J16: Project Plan | K16: Open | L16: Add details | M16: Record which folders, repos and tools each person has been given, and by when. Access granted late is schedule lost silently. | N16: Project Manager | O16: Project Manager / IT | P16: Provision Drive folder tree access, repository access, EDA licences and tracker access on day one. Confirm by asking each person to open the thing, not by checking the grant was issued — permission inherited from a parent folder frequently does not resolve as expected. Access delays are invisible in status reporting and show up a week later as unexplained slip.
A17: 12 | B17: 1 · Pre-design Feasibility | C17: Market & Competitor Study | D17: Project sanctioned and vision agreed | E17: Market study documented with competitor benchmark table | F17: Do we know what already exists in this category and at what price? | G17: Has the study changed or confirmed any assumption in the LLD? | H17: [ProjectID]_Market-and-Competitor-Study_v1.0 | I17: EB-T-141 | J17: Product Features & Risk Management | K17: Open | L17: Add details | M17: Add the competitor benchmark table: each competing product, its price, and how it scores against your feature list. Note where you are worse and why that is acceptable. | N17: Project Manager | O17: Product / Project Manager | P17: Map the category: who sells into it, at what price, with what feature set and what certifications. Use EXIM data where import volumes tell you more than marketing pages. The purpose is to challenge our assumptions, not to justify them — a study that confirms everything we already believed was not a study. Feed anything that contradicts the LLD back into the LLD review step.
... A310: 305 | B310: 2 · DFx — Manufacturability and Test | C310: DFM/DFT checklist closure and house standard update | D310: G3 released and the first production run complete | E310: Checklist frozen as the project's DFx record, and every finding the checklist did not already ask for added to the house standard | F310: What did this project teach us that the checklist did not already ask? | G310: Has the house standard been updated, versioned and issued so the next project starts from it? | H310: EB-T-228 · [ProjectID]_DFx-Lessons-Learned_v1.0 | I310: EB-T-228 | J310: DFM/DFT Lessons Learned and House Standard Update | K310: Open | L310: Create from template | M310: Create the lessons sheet and turn every problem found outside the checklist into a proposed new check with a gate, a severity and a parameter. Then version the house standard. | N310: Project Manager | O310: Hardware Engineer / Process Owner | P310: Freeze a copy of the completed checklist as the project record, then do the part everybody skips: take the problems that were found outside the checklist and turn each one into a new check with a gate, a severity and, where a number is involved, a parameter. A checklist that never grows is a checklist that keeps missing the same things. Version the house standard and tell the next project it changed.

Sheet Flow Map
A1: Eb-ODM — Flow Structure: where the process splits and merges
A3: Block | B3: Category | C3: Source rows (Sheet1) | D3: Steps | E3: Runs | F3: Converges with
A4: A — Serial | B4: 1 · Pre-design Feasibility | C4: 20–49 | D4: 32 | E4: Sequential (entry: PO received) | F4: SPLIT after 'Trial Hardware BOM Ordering' (row 49)
A5: B — Parallel | B5: 2 · Design — Hardware | C5: 52–121 col B | D5: 71 | E5: Concurrent track 1 | F5: Test Reports → Prototype Checklist
A6: B — Parallel | B6: 2 · Design — Firmware | C6: 52–81 col C | D6: 31 | E6: Concurrent track 2 | F6: Test Reports → Prototype Checklist
A7: B — Parallel | B7: 2 · Design — Enclosure | C7: 52–88 col D | D7: 38 | E7: Concurrent track 3 | F7: Test Reports → Prototype Checklist
A8: B — Parallel | B8: 3 · Test (per track) | C8: per track, inline | D8: 39 | E8: One per track | F8: MERGE at Prototype Checklist
A9: B — Gate | B9: 2 · DFx — Manufacturability and Test | C9: interleaved by gate | D9: 19 | E9: Gated: G0 → G1 → G2 → G3 | F9: Blocks layout start, fab release and production release
A10: C — Serial | B10: 4 · Prototype | C10: 126–143 | D10: 20 | E10: Sequential (merged) | F10: → Pilot
A11: C — Serial | B11: 5 · Pilot | C11: 145–159 | D11: 16 | E11: Sequential | F11: → Mass Production
A12: C — Serial | B12: 6 · Mass Production | C12: 160–183 | D12: 26 | E12: Sequential | F12: → Project closure
A13: C — Serial | B13: 3 · Test (system) | C13: post-merge | D13: 13 | E13: Sequential (after Prototype) | F13: → Pilot
C14: TOTAL | D14: =SUM(D4:D13)
A18: Cross-track convergence points (the three parallel tracks must synchronise here)
A20: # | B20: Convergence step | C20: Tracks | D20: What must be agreed
A21: 1 | B21: Block diagram review with FW & Enclosure team | C21: HW ↔ FW ↔ ENC | D21: Interfaces, peripheral map, board outline intent
A22: 2 | B22: Schematic review with FW & Enclosure team | C22: HW ↔ FW ↔ ENC | D22: Pin map, connectors, mechanical constraints
A23: 3 | B23: Board Outline review with Enclosure team | C23: HW ↔ ENC | D23: Outline and keep-outs against enclosure CAD revision
A24: 4 | B24: PCB STEP File review with enclosure team | C24: HW ↔ ENC | D24: Interference and clearance at worst-case tolerance
A25: 5 | B25: Concept / CAD / render reviews with HW team | C25: ENC ↔ HW | D25: Internal volume, mounting, thermal path
A26: 6 | B26: Mechanical BoM Review with HW & FW | C26: ENC ↔ HW ↔ FW | D26: Combined BOM builds a complete unit
A27: 7 | B27: Prototype Checklist (row 126) | C27: MERGE POINT | D27: All three tracks' outputs reconcile at one revision

Sheet Summary
A1: Category summary
A3: Category | B3: Step count | C3: % of process
A4: 1 · Pre-design Feasibility | B4: =COUNTIF('Process Flow'!$B$6:$B$310,$A4) | C4: =IFERROR($B4/$B$13,0)
A5: 2 · Design — Hardware | B5: =COUNTIF('Process Flow'!$B$6:$B$310,$A5) | C5: =IFERROR($B5/$B$13,0)
A6: 2 · Design — Firmware | B6: =COUNTIF('Process Flow'!$B$6:$B$310,$A6) | C6: =IFERROR($B6/$B$13,0)
A7: 2 · Design — Enclosure | B7: =COUNTIF('Process Flow'!$B$6:$B$310,$A7) | C7: =IFERROR($B7/$B$13,0)
A8: 3 · Test | B8: =COUNTIF('Process Flow'!$B$6:$B$310,$A8) | C8: =IFERROR($B8/$B$13,0)
A9: 4 · Prototype | B9: =COUNTIF('Process Flow'!$B$6:$B$310,$A9) | C9: =IFERROR($B9/$B$13,0)
A10: 5 · Pilot | B10: =COUNTIF('Process Flow'!$B$6:$B$310,$A10) | C10: =IFERROR($B10/$B$13,0)
A11: 6 · Mass Production | B11: =COUNTIF('Process Flow'!$B$6:$B$310,$A11) | C11: =IFERROR($B11/$B$13,0)
A12: 2 · DFx — Manufacturability and Test | B12: =COUNTIF('Process Flow'!$B$6:$B$310,$A12) | C12: =IFERROR($B12/$B$13,0)
A13: TOTAL | B13: =SUM($B$4:$B$12) | C13: =IFERROR($B$13/$B$13,0)

Sheet Template Actions
A1: Eb-ODM — Template Actions
A2: Every template in the library, and which process steps write to it. Read this the other way round from the Process Flow tab.
A4: Template ID | B4: Template to work on | C4: Open | D4: Folder | E4: Steps that touch it | F4: Times | G4: Actions used
A5: EB-T-001 | B5: Audit Checklist | C5: Open | D5: 00-Governance/ | E5: 31, 113, 114, 128, 157, 160, 173, 211, 212, 224, 245, 246, 260, 276, 303, 304 | F5: 16 | G5: Create from template · Update details · Review & mark · Approve / Release
A6: EB-T-002 | B6: Audit Checklist Scope Record | C6: Open | D6: 00-Governance/ | E6: 32 | F6: 1 | G6: Create from template
A7: EB-T-010 | B7: Hardware Design Document (HDD) | C7: Open | D7: 02-Hardware/00-Design/ | E7: 37, 42, 44, 45, 46, 47, 48, 64 | F7: 8 | G7: Create from template · Add details
A8: EB-T-011 | B8: Reference Product Teardown | C8: Open | D8: 02-Hardware/00-Design/ | E8: 13, 14, 15 | F8: 3 | G8: Create from template · Add details
A9: EB-T-012 | B9: Components Selection Criteria | C9: Open | D9: 02-Hardware/00-Design/ | E9: 55 | F9: 1 | G9: Add details
A10: EB-T-013 | B10: Design Notes | C10: Open | D10: 02-Hardware/00-Design/ | E10: 56, 57, 66, 72 | F10: 4 | G10: Add details · Record result
A11: EB-T-014 | B11: Product Datasheet | C11: Open | D11: 02-Hardware/00-Design/ | E11: 99, 100 | F11: 2 | G11: Review & mark · Approve / Release
A12: EB-T-015 | B12: User Manual | C12: Open | D12: 02-Hardware/00-Design/ | E12: 104 | F12: 1 | G12: Approve / Release
A13: EB-T-017 | B13: Bill of Material (Eb BOM format) | C13: Open | D13: 02-Hardware/00-Design/ | E13: 30, 60 | F13: 2 | G13: Create from template · Approve / Release
A14: EB-T-018 | B14: Design Review Record | C14: Open | D14: 02-Hardware/00-Design/Design-Review/ | E14: 40, 54, 65, 82, 83, 132, 135, 140, 152, 177, 178, 180, 181, 185, 186, 187, 190, 192, 193, 194, 203 | F14: 21 | G14: Add details · Review & mark · Approve / Release
A15: EB-T-019 | B15: Block Diagram Review Checklist | C15: Open | D15: 02-Hardware/00-Design/Design-Review/ | E15: 38, 39, 130, 131 | F15: 4 | G15: Review & mark
A16: EB-T-020 | B16: Schematic Review Checklist | C16: Open | D16: 02-Hardware/00-Design/Design-Review/ | E16: 50, 51 | F16: 2 | G16: Review & mark
... A135: EB-T-228 | B135: DFM/DFT Lessons Learned and House Standard Update | C135: Open | D135: 02-Project-Folder-R&D-PM/08-DFx-and-Manufacturing-Readiness/04-Lessons-Learned/ | E135: 305 | F135: 1 | G135: Create from template

Sheet Read Me
A1: Eb-ODM Master Process Flow
A3: Source | B3: Eb_ODM_Process_Steps_FULL.xlsx · Sheet1 (Category + Steps), rows 20–183. Downloaded from Drive 15-Aug-2026, file modified 08:11 that morning. Steps and categories are reproduced verbatim; the nine added columns are new.
A4: Step count | B4: 305. Was 227 at source; 45 test steps, then 14 Audit Checklist steps, then 19 DFM/DFT steps added Aug-2026. Sequential pre-design → three parallel design tracks → per-track test → merge at Prototype Checklist → post-merge system test → Pilot → Mass Production, with the DFx gates cutting across all of it.
A5: Sales excluded | B5: The 15 Sales steps at source rows 5–19 are deliberately out of scope. The process now opens at Product strategy fit & sanction by Management, whose entry trigger is PO received and project handed to PM — that PO is the boundary of what this document covers. Category numbering has been closed up so it runs 1–6 with no gap.
A6: Split point | B6: Sheet1 row 49, 'Trial Hardware BOM Ordering'. Immediately after it the process divides into Hardware, Firmware and Enclosure running concurrently.
A7: Merge point | B7: Sheet1 row 126, 'Prototype Checklist'. All three tracks' outputs must reconcile at one consistent revision here.
A9: Owner | B9: Set to Project Manager on every row, per the brief. The PM is accountable for the gate — that a step opened when it should and closed when it genuinely met its exit criteria. This is deliberately separate from who does the work.
A10: Responsibility | B10: The function that performs the work. Where two or more are named, all must participate; it is not a choice between them. Shared accountability remains prohibited — Responsibility can be shared, Owner cannot.
A11: Entry / Exit Trigger | B11: The observable event that opens and closes the step. A trigger is an event, not a date.
A12: Entry / Exit Question | B12: The gate question. If the Entry Question cannot be answered yes, the step does not start. If the Exit Question cannot be answered yes with evidence, the step is not done — regardless of how much work was performed.
A13: Template Link | B13: The target filename under the Elecbits naming convention [ProjectID]_FileName_v1.0. These are targets to be created, not live URLs. No template repository exists for most of these yet; populating this column is a separate workstream.
A14: Guidelines | B14: Written per step. Each states how to actually perform the step and, where relevant, why the common failure mode occurs. These are guidance, not a substitute for the domain SOP where one exists.
A16: Duplicated step names | B16: Three enclosure steps (Design Approval, 3D Printing, Prototype Fit & Assembly Check) appear twice in the source — they form the design iteration loop. The second occurrence is marked '(iteration 2)'. 'Legal paperwork - NDA' appears twice under Mass Production and has been disambiguated as Enclosure vendor and BoM vendor.
... A19: Open items to confirm | B19: 1. Whether Owner should stay Project Manager on every row or vary by category — the brief specified PM throughout.
B20: 2. Template repository location, before the Template Link column can hold real links.
B21: 3. Whether the three parallel tracks are permitted to start simultaneously, or whether Firmware and Enclosure wait on the Hardware block diagram release. The source shows all three starting at System Block Diagram.
B22: 4. Ideal duration per step is not in the source and is not included here. It is the A5 attribute from the 7-Aug MoM embedding schema and remains unfilled across the process corpus.
A24: Test steps added | B24: 12 hardware, 10 firmware, 10 enclosure test-execution steps inserted immediately before each existing 'Test Reports' step, plus 13 post-merge system and compliance steps inserted between Prototype and Pilot. Test moves from 3 steps to 48. Every test family follows the three-artefact rule: parameter document, procedure document, then test-and-report. No existing row was altered, reordered or removed.
A26: Audit Checklist steps | B26: 14 steps added so the Audit Checklist is created, scoped and written to at every stage rather than only referenced. Created and scoped at pre-design (one tab per board, every row marked Required / Conditional / Not-Applicable with a reason). Written to at the close of each design track, after each test block, at assembly, at the pilot-release gate, after system and compliance testing, at pilot build, at EMS handover, and frozen at closure. Every update step requires four cells on each Required row: Status, Link, Last updated and Updated by. No previously existing row was altered, reordered or removed.
A28: DFM / DFT steps | B28: 19 steps added under the category '2 · DFx — Manufacturability and Test' so the DFx thread is filterable as one stage while each step still sits at the moment its gate actually bites. G0 design input closes before layout begins — standards baseline, fabricator and EMS capability capture, parameter agreement, gate sign-off. Four DFT steps then run on the finished layout: test point coverage analysis, probe access and fixture feasibility, programming and debug access, and disposition of every net that cannot be reached. G1 closes after the two existing DFx checklist reviews; G2 after DFx sign-off, together with waiver register closure. Firmware gains a diagnostic command set step and a production programming and provisioning step; enclosure gains a moulder capability review. Before fab ordering, the three tracks are consolidated into one product-level DFx view and a written fab and assembly release authorisation. G3 closes in Mass Production after fixture coverage verification, followed by checklist closure and a house standard update. Every step points at the DFM/DFT Master Checklist (EB-T-023) or one of the supporting DFx templates. No previously existing row was altered, reordered or removed. The one exception is the Template Link cell on 14 existing DFx steps — DFM considerations, DFA considerations, both DFx checklist reviews, the DFS, DFC and DFE reviews, DFx Action Item Closure, DFx Sign-off, Enclosure DFMA, DFMA report, MFA Report, DFMEA and PFMEA — which previously named a file that did not exist and now quote a Template ID from the register. Step text, triggers, questions, owner, responsibility and guidelines on those rows are unchanged.
A1002: Template & action columns | B1002: Five columns added after Template Link: Template ID, Template to work on, Open, Action and What to do in the template. Every one of the 305 steps now names exactly one template from the 176-template library, and the Template ID and Open cells link straight to that file in Drive. Action is a controlled list of eight values — Create from template, Add details, Update details, Populate parameters, Record result, Review & mark, Approve / Release, Reference only — so the column can be filtered and counted. 'What to do in the template' is the baseline instruction: which tab, which fields, and what makes the entry good enough to close the step. The Template Actions tab reads the same data the other way round — one row per template, listing every step that writes to it. No existing column, row or value was changed.
