Workbook

Sheet Index
D2: Template Index
D3: Eb-ODM · every template, what it is, where it lives, and a link that opens it
A5: Register | D5: Eb-ODM Template Library | J5: Version | M5: v5.0
A6: Owner | D6: Process Owner | J6: Templates | M6: 178
A7: Linked to Drive | D7: 176 of 178 | J7: Source | M7: Master Process Flow v4 · 305 steps
A8: Last Updated | J8: Updated By
A10: Template ID | B10: Template Name | C10: Open | D10: Format | E10: Category | F10: Description & Use Case | G10: What Good Looks Like | H10: Serves | I10: Folder (in eb-templates) | J10: Instance Path (in project folder) | K10: Instance Naming | L10: Stage | M10: Created at Step | N10: Edited at Steps | O10: Template Owner | P10: Filled By | Q10: Audit Checklist Row | R10: Version
A11: EB-T-001 | B11: Audit Checklist | C11: Open | D11: xlsx | E11: Governance | F11: The exit artefact for the whole folder. Every step that produces an artefact writes four cells against its row: Status, Link, Last updated, Updated by. | G11: Every Required row carries all four cells; no row left at 'Not checked' when the gate is claimed | H11: Both | I11: 02-PCB-ID-Folder-Engineering/00-Governance/ | J11: 00-Audit-Checklist.xlsx | K11: [PCB-ID]_Audit-Checklist_v1.0 | L11: All | M11: 1.31 | N11: every stage | O11: Process Owner | P11: All roles | Q11: — (is the checklist) | R11: v1.0
A12: EB-T-002 | B12: Audit Checklist Scope Record | C12: Open | D12: xlsx | E12: Governance | F12: Scopes the checklist to this specific product so completion percentage means something. Without it people bulk-fill 'Not started' across rows that will never apply. | G12: Every Not-Applicable row carries a written reason and a PM signature | H12: Both | I12: 02-PCB-ID-Folder-Engineering/00-Governance/ | J12: 00-Audit-Checklist-Scope.xlsx | K12: [PCB-ID]_Audit-Checklist-Scope_v1.0 | L12: 1 | M12: 1.32 | N12: — | O12: Process Owner | P12: Project Manager | Q12: — (scopes the checklist) | R12: v1.0
A13: EB-T-003 | B13: Client Input Log | C13: Open | D13: xlsx | E13: PM | F13: Register of everything the client supplied: spec, datasheets, reference designs, constraints. Tracks version and date received. | G13: Every client file has a row with the version received and the date, so 'which spec did we build to' is answerable | H13: PCB ID folder | I13: 02-PCB-ID-Folder-Engineering/01-Input-from-Client/ | J13: 01-Input-from-Client/ | K13: [PCB-ID]_Client-Input-Log_v1.0 | L13: 1 | M13: 1.05 | N13: 2.x | O13: Project Manager | P13: Project Manager | Q13: HW 1-3 | R13: v1.0
A14: EB-T-010 | B14: Hardware Design Document (HDD) | C14: Open | D14: xlsx | E14: Hardware | F14: The hardware specification: architecture, interfaces, power budget, component decisions and their rationale. | G14: Every design decision carries a reason, not just a value | H14: PCB ID folder | I14: 02-PCB-ID-Folder-Engineering/02-Hardware/00-Design/ | J14: 02-Hardware/00-Design/Documentation/ | K14: [PCB-ID]_HDD_v1.0 | L14: 2 | M14: 2.04 | N14: 2.x | O14: Hardware Lead | P14: Hardware Engineer | Q14: HW 4 | R14: v1.0
A15: EB-T-011 | B15: Reference Product Teardown | C15: Open | D15: docx | E15: Hardware | F15: Findings from physically taking apart a comparable market product — architecture, component choices, cost signals, failure points. | G15: Learnings are component-level and reusable, not a photo album | H15: PCB ID folder | I15: 02-PCB-ID-Folder-Engineering/02-Hardware/00-Design/ | J15: 02-Hardware/00-Design/Documentation/ | K15: [PCB-ID]_Reference-Teardown_v1.0 | L15: 1 | M15: 1.12 | N15: — | O15: Hardware Engineer | P15: Hardware Engineer | Q15: HW 2 | R15: v1.0
A16: EB-T-012 | B16: Components Selection Criteria | C16: Open | D16: xlsx | E16: Hardware | F16: Why each key component was chosen: alternates considered, lead time, cost, second source, and the decision rationale. | G16: Every single-source part has a named alternate or a written reason it has none | H16: PCB ID folder | I16: 02-PCB-ID-Folder-Engineering/02-Hardware/00-Design/ | J16: 02-Hardware/00-Design/Documentation/ | K16: [PCB-ID]_Components-Selection_v1.0 | L16: 2 | M16: 2.06 | N16: 2.x | O16: Solution Architect | P16: Hardware Engineer | Q16: HW 5 | R16: v1.0
A17: EB-T-013 | B17: Design Notes | C17: Open | D17: docx | E17: Hardware | F17: Running notes on design decisions, trade-offs and things discovered during the work. | G17: A later engineer can understand why the board looks the way it does | H17: PCB ID folder | I17: 02-PCB-ID-Folder-Engineering/02-Hardware/00-Design/ | J17: 02-Hardware/00-Design/Documentation/ | K17: [PCB-ID]_Design-Notes_v1.0 | L17: 2 | M17: 2.08 | N17: 2.x | O17: Hardware Engineer | P17: Hardware Engineer | Q17: HW 6 | R17: v1.0
A18: EB-T-014 | B18: Product Datasheet | C18: Open | D18: docx | E18: Hardware | F18: The customer-facing specification of the finished board: ratings, interfaces, environmental limits, mechanical data. | G18: Every number in it has been measured, not estimated | H18: Both | I18: 02-PCB-ID-Folder-Engineering/02-Hardware/00-Design/ | J18: 02-Hardware/00-Design/Documentation/ | K18: [PCB-ID]_Product-Datasheet_v1.0 | L18: 6 | M18: 6.14 | N18: — | O18: Hardware Lead | P18: Hardware Engineer | Q18: HW 7 | R18: v1.0
A19: EB-T-015 | B19: User Manual | C19: Open | D19: docx | E19: Hardware | F19: How the end user installs, operates and troubleshoots the product. | G19: Describes real behaviour, verified against a real unit, not intended behaviour | H19: Both | I19: 01-Project-ID-Folder-PM/02-Project-Folder-R&D-PM/15-User-Manual-Product-Datasheet/ | J19: 02-Hardware/00-Design/Documentation/ | K19: [PCB-ID]_User-Manual_v1.0 | L19: 6 | M19: 6.15 | N19: — | O19: Project Manager | P19: Hardware Engineer | Q19: HW 8 | R19: v1.0
A20: EB-T-016 | B20: Power Profiling & Thermal | C20: Open | D20: xlsx | E20: Hardware | F20: Current draw and thermal behaviour per mode, per rail, at worst-case load. | G20: Peak temperatures logged against each component's rated max with derating applied | H20: Both | I20: 02-PCB-ID-Folder-Engineering/02-Hardware/00-Design/ | J20: 02-Hardware/00-Design/Documentation/ | K20: [PCB-ID]_Power-Profiling_v1.0 | L20: 2 | M20: 2.11 | N20: 3.x | O20: Hardware Engineer | P20: Hardware Engineer | Q20: HW 9 | R20: v1.0
A21: EB-T-017 | B21: Bill of Material (Eb BOM format) | C21: Open | D21: xlsx | E21: Hardware | F21: The electrical bill of material for a specific board revision. | G21: Every line has a manufacturer part number and at least one alternate where single-sourced | H21: PCB ID folder | I21: 02-PCB-ID-Folder-Engineering/02-Hardware/00-Design/ | J21: 02-Hardware/01-Outputs/Rev-N/BOM/ | K21: [PCB-ID]_BOM_Rev0 | L21: 2 | M21: 2.20 | N21: every rev | O21: Hardware Engineer | P21: Hardware Engineer | Q21: HW 16 | R21: v1.0
... A188: EB-T-228 | B188: DFM/DFT Lessons Learned and House Standard Update | C188: Open | D188: xlsx | E188: DFx | F188: Every problem this project hit that the checklist did not already ask about, converted into a proposed new check with a gate, a severity and a parameter. | G188: It ends with a versioned house standard update issued to the next project — a checklist that never grows keeps missing the same things | H188: Project Management folder | I188: 01-Project-ID-Folder-PM/02-Project-Folder-R&D-PM/08-DFx-and-Manufacturing-Readiness/04-Lessons-Learned/ | J188: 02-Project-Folder-R&D-PM/08-DFx-and-Manufacturing-Readiness/04-Lessons-Learned/ | K188: [ProjectID]_DFx-Lessons-Learned_v1.0 | L188: 6 | M188: 6.305 | N188: — | O188: Process Owner | P188: Hardware Engineer / Process Owner | Q188: PM | R188: v1.0

Sheet Duplicates in Drive
C2: Duplicates in Drive
C3: Same Template ID, two files. Keep one, trash the other.
A5: Register | B5: Eb-ODM Template Library | C5: Version | D5: v5.0
A6: Duplicate IDs | B6: 6 | C6: Extra files | D6: 6
A7: Last Updated | C7: Updated By
A9: These Template IDs resolve to more than one file in Drive — almost certainly a v2 copy left behind when v3 was uploaded. The Index links to the first of each pair. Delete the other so there is one file per Template ID.
A11: Template ID | B11: File name | C11: Copy | D11: Open
A12: EB-T-001 | B12: EB-T-001_Audit-Checklist.xlsx | C12: 1 of 2 | D12: Open
A13: EB-T-001 | B13: EB-T-001_Audit-Checklist.xlsx | C13: 2 of 2 | D13: Open
A14: EB-T-002 | B14: EB-T-002_Audit-Checklist-Scope-Record.xlsx | C14: 1 of 2 | D14: Open
A15: EB-T-002 | B15: EB-T-002_Audit-Checklist-Scope-Record.xlsx | C15: 2 of 2 | D15: Open
A16: EB-T-003 | B16: EB-T-003_Client-Input-Log.xlsx | C16: 1 of 2 | D16: Open
A17: EB-T-003 | B17: EB-T-003_Client-Input-Log.xlsx | C17: 2 of 2 | D17: Open
A18: EB-T-023 | B18: EB-T-023_DFM-DFT-Master-Checklist.xlsx | C18: 1 of 2 | D18: Open
A19: EB-T-023 | B19: EB-T-023_DFM-DFT-Master-Checklist.xlsx | C19: 2 of 2 | D19: Open
A20: EB-T-024 | B20: EB-T-024_Revision-Index.xlsx | C20: 1 of 2 | D20: Open
A21: EB-T-024 | B21: EB-T-024_Revision-Index.xlsx | C21: 2 of 2 | D21: Open
A22: EB-T-025 | B22: EB-T-025_Current-Revision-Record.xlsx | C22: 1 of 2 | D22: Open
A23: EB-T-025 | B23: EB-T-025_Current-Revision-Record.xlsx | C23: 2 of 2 | D23: Open

Sheet Summary
D2: Summary
D3: Live counts from the Index tab
A5: Register | B5: Eb-ODM Template Library | D5: Version | E5: v5.0
A6: Total Templates | B6: 178 | D6: Linked to Drive | E6: 176 of 178
A7: Last Updated | D7: Updated By
A9: By folder served
A10: Value | B10: Count | C10: % of total
A11: PCB ID folder | B11: =COUNTIF(Index!$H$11:$H$188,$A11) | C11: =IFERROR($B11/178,0)
A12: Project Management folder | B12: =COUNTIF(Index!$H$11:$H$188,$A12) | C12: =IFERROR($B12/178,0)
A13: Both | B13: =COUNTIF(Index!$H$11:$H$188,$A13) | C13: =IFERROR($B13/178,0)
A15: By category
A16: Value | B16: Count | C16: % of total
A17: Assembly | B17: =COUNTIF(Index!$E$11:$E$188,$A17) | C17: =IFERROR($B17/178,0)
A18: Builds | B18: =COUNTIF(Index!$E$11:$E$188,$A18) | C18: =IFERROR($B18/178,0)
A19: Closure | B19: =COUNTIF(Index!$E$11:$E$188,$A19) | C19: =IFERROR($B19/178,0)
A20: DFx | B20: =COUNTIF(Index!$E$11:$E$188,$A20) | C20: =IFERROR($B20/178,0)
A21: Delivery | B21: =COUNTIF(Index!$E$11:$E$188,$A21) | C21: =IFERROR($B21/178,0)
A22: Enclosure | B22: =COUNTIF(Index!$E$11:$E$188,$A22) | C22: =IFERROR($B22/178,0)
A23: Firmware | B23: =COUNTIF(Index!$E$11:$E$188,$A23) | C23: =IFERROR($B23/178,0)
A24: Governance | B24: =COUNTIF(Index!$E$11:$E$188,$A24) | C24: =IFERROR($B24/178,0)
A25: Hardware | B25: =COUNTIF(Index!$E$11:$E$188,$A25) | C25: =IFERROR($B25/178,0)
A26: PM | B26: =COUNTIF(Index!$E$11:$E$188,$A26) | C26: =IFERROR($B26/178,0)
A27: SCS | B27: =COUNTIF(Index!$E$11:$E$188,$A27) | C27: =IFERROR($B27/178,0)
A28: System Test | B28: =COUNTIF(Index!$E$11:$E$188,$A28) | C28: =IFERROR($B28/178,0)
A29: Test | B29: =COUNTIF(Index!$E$11:$E$188,$A29) | C29: =IFERROR($B29/178,0)
A31: By stage
A32: Value | B32: Count | C32: % of total
A33: 1 | B33: =COUNTIF(Index!$L$11:$L$188,$A33) | C33: =IFERROR($B33/178,0)
A34: 2 | B34: =COUNTIF(Index!$L$11:$L$188,$A34) | C34: =IFERROR($B34/178,0)
A35: 3 | B35: =COUNTIF(Index!$L$11:$L$188,$A35) | C35: =IFERROR($B35/178,0)
A36: 4 | B36: =COUNTIF(Index!$L$11:$L$188,$A36) | C36: =IFERROR($B36/178,0)
A37: 5 | B37: =COUNTIF(Index!$L$11:$L$188,$A37) | C37: =IFERROR($B37/178,0)
A38: 6 | B38: =COUNTIF(Index!$L$11:$L$188,$A38) | C38: =IFERROR($B38/178,0)
A39: All | B39: =COUNTIF(Index!$L$11:$L$188,$A39) | C39: =IFERROR($B39/178,0)
A41: By format
A42: Value | B42: Count | C42: % of total
A43: xlsx | B43: =COUNTIF(Index!$D$11:$D$188,$A43) | C43: =IFERROR($B43/178,0)
A44: docx | B44: =COUNTIF(Index!$D$11:$D$188,$A44) | C44: =IFERROR($B44/178,0)

Sheet Read Me
C2: Read Me
C3: How this register works
A5: Register | B5: Eb-ODM Template Library | C5: Version | D5: v5.0
A6: Owner | B6: Process Owner | C6: Templates | D6: 178
A7: Last Updated | C7: Updated By
A9: Item | B9: Detail
A10: Purpose | B10: The single register of every template in the ODM system. The Master Process Flow points at a Template ID; this tells you what it is, where it lives, when it is touched, and gives you a link that opens it.
A11: Open | B11: Click 'Open' — or the Template ID itself — to open the blank template in Drive. Every one of the 176 rows links to a real file.
A12: Template ID | B12: EB-T-nnn. Stable — it never changes even if the template is renamed, because the process sheet references it.
A13: Folder | B13: Where the blank lives inside eb-templates. One canonical copy; project folders copy from it and never the other way round.
A14: Instance Path | B14: Where the filled copy belongs in the PCB ID or Project Management folder, per the approved sitemaps.
A15: Instance Naming | B15: The filename the filled copy takes. [ProjectID] or [PCB-ID] is replaced with the real ID.
A16: Created at Step / Edited at Steps | B16: The lifecycle, against the 305-step Master Process Flow. Created at exactly one step; edited at any number. This is what answers 'the same file appears in several steps'.
A17: Serves | B17: Which of the two sections the template belongs to — the PM's Project ID folder, the engineer's PCB ID folder, or both.
A18: Template Owner / Filled By | B18: Owner maintains the blank. Filled By is the role that puts content in the copy.
A19: Audit Checklist Row | B19: Which row of the audit checklist this artefact evidences. The link between a template and the exit gate.
A20: Standard header block | B20: Every template opens with Template ID, Template Version, Project ID, PCB ID, Revision, Created at Step, Last Updated, Updated By. Yellow cells are for the user to fill.
... A23: Duplicates in Drive | B23: Six Template IDs currently resolve to two files each — see that tab. Trash the extra copy so one ID means one file.
